{"stats":{"minecraft:picked_up":{"hat:farmerhat":13,"hat:tophat":2,"hat:armorerhat":1},"minecraft:custom":{"minecraft:open_barrel":1,"minecraft:time_since_rest":97364,"minecraft:crouch_one_cm":3987,"minecraft:play_time":97364,"minecraft:sprint_one_cm":198775,"minecraft:walk_one_cm":123715,"minecraft:sneak_time":1589,"minecraft:mob_kills":2,"minecraft:drop":29,"minecraft:jump":158,"minecraft:damage_dealt":400,"minecraft:leave_game":179,"minecraft:time_since_death":97364,"minecraft:traded_with_villager":92,"minecraft:total_world_time":239805,"minecraft:talked_to_villager":23,"minecraft:fall_one_cm":418,"minecraft:fly_one_cm":171679},"minecraft:killed":{"minecraft:villager":2},"minecraft:dropped":{"hat:tophat":2,"hat:farmerhat":13,"hat:armorerhat":1,"minecraft:cake":11},"minecraft:used":{"hat:farmerhat":3,"minecraft:brewing_stand":1,"minecraft:sand":4,"minecraft:villager_spawn_egg":6,"minecraft:flint_and_steel":3,"minecraft:loom":1,"minecraft:armor_stand":9,"minecraft:netherite_axe":4,"minecraft:smooth_stone_slab":2,"minecraft:lectern":1,"minecraft:composter":4,"minecraft:stonecutter":2,"minecraft:barrel":1},"minecraft:crafted":{"minecraft:apple":64,"minecraft:cookie":432,"minecraft:cake":12,"minecraft:pumpkin_pie":48,"minecraft:emerald":26,"minecraft:air":0,"minecraft:suspicious_stew":2}},"DataVersion":2975}